{"url":"http:\/\/localhost:8080\/index.php\/statistique\/acceuil1\/0","method":"GET","isAJAX":true,"startTime":1733841109.2047,"totalTime":47.7,"totalMemory":"3.122","segmentDuration":10,"segmentCount":5,"CI_VERSION":"4.3.6","collectors":[{"title":"Timers","titleSafe":"timers","titleDetails":"","display":[],"badgeValue":null,"isEmpty":false,"hasTabContent":false,"hasLabel":false,"icon":"","hasTimelineData":true,"timelineData":[{"name":"Bootstrap","component":"Timer","start":1733841109.207329,"duration":0.031729936599731445},{"name":"Routing","component":"Timer","start":1733841109.239061,"duration":0.00019478797912597656},{"name":"Before Filters","component":"Timer","start":1733841109.239738,"duration":2.09808349609375e-5},{"name":"Controller","component":"Timer","start":1733841109.239761,"duration":0.01258397102355957},{"name":"Controller Constructor","component":"Timer","start":1733841109.239761,"duration":0.00021982192993164062},{"name":"After Filters","component":"Timer","start":1733841109.252392,"duration":0.0002410411834716797}]},{"title":"Database","titleSafe":"database","titleDetails":"(6 total Queries, 6 of them unique across 1 Connection)","display":{"queries":[{"hover":"","class":"","duration":"1.47 ms","sql":"<strong>SELECT<\/strong> *\n<strong>FROM<\/strong> `year`\n<strong>WHERE<\/strong> `status_year` = 0\n<strong>AND<\/strong> `etat_year` = &#039;actif&#039;","trace":[{"file":"SYSTEMPATH\/Database\/BaseBuilder.php:1616","function":"\u00a0\u00a0\u00a0\u00a0\u00a0\u00a0\u00a0\u00a0CodeIgniter\\Database\\BaseConnection->query()","index":"\u00a0\u00a01\u00a0\u00a0\u00a0\u00a0"},{"file":"APPPATH\/Models\/YearModel.php:72","function":"\u00a0\u00a0\u00a0\u00a0\u00a0\u00a0\u00a0\u00a0CodeIgniter\\Database\\BaseBuilder->get()","index":"\u00a0\u00a02\u00a0\u00a0\u00a0\u00a0"},{"file":"APPPATH\/Controllers\/StatistiqueController.php:34","function":"\u00a0\u00a0\u00a0\u00a0\u00a0\u00a0\u00a0\u00a0App\\Models\\YearModel->getYearActif()","index":"\u00a0\u00a03\u00a0\u00a0\u00a0\u00a0"},{"file":"SYSTEMPATH\/CodeIgniter.php:932","function":"\u00a0\u00a0\u00a0\u00a0\u00a0\u00a0\u00a0\u00a0App\\Controllers\\StatistiqueController->statistique1()","index":"\u00a0\u00a04\u00a0\u00a0\u00a0\u00a0"},{"file":"SYSTEMPATH\/CodeIgniter.php:497","function":"\u00a0\u00a0\u00a0\u00a0\u00a0\u00a0\u00a0\u00a0CodeIgniter\\CodeIgniter->runController()","index":"\u00a0\u00a05\u00a0\u00a0\u00a0\u00a0"},{"file":"SYSTEMPATH\/CodeIgniter.php:366","function":"\u00a0\u00a0\u00a0\u00a0\u00a0\u00a0\u00a0\u00a0CodeIgniter\\CodeIgniter->handleRequest()","index":"\u00a0\u00a06\u00a0\u00a0\u00a0\u00a0"},{"file":"FCPATH\/index.php:67","function":"\u00a0\u00a0\u00a0\u00a0\u00a0\u00a0\u00a0\u00a0CodeIgniter\\CodeIgniter->run()","index":"\u00a0\u00a07\u00a0\u00a0\u00a0\u00a0"},{"file":"SYSTEMPATH\/Commands\/Server\/rewrite.php:47","args":["\/home\/takam\/Bureau\/ecole-negou-new\/public\/index.php"],"function":"\u00a0\u00a0\u00a0\u00a0\u00a0\u00a0\u00a0\u00a0require_once()","index":"\u00a0\u00a08\u00a0\u00a0\u00a0\u00a0"}],"trace-file":"APPPATH\/Models\/YearModel.php:72","qid":"b0bcce752e4e48ece35f3625cfa9531c"},{"hover":"","class":"","duration":"0.36 ms","sql":"<strong>SELECT<\/strong> `teacher`.`matricule`, `teacher`.`name`, `teacher`.`surname`, `teacher`.`diplome`, `teacher`.`login`, `teacher`.`photo`, `teacher`.`tel`, `teacher`.`sexe`, `teacher`.`email`\n<strong>FROM<\/strong> `teacher`\n<strong>INNER<\/strong> <strong>JOIN<\/strong> `year` <strong>ON<\/strong> `year`.`year_id`=`teacher`.`year_id`\n<strong>WHERE<\/strong> `teacher`.`year_id` = 1\n<strong>AND<\/strong> `teacher`.`status_teacher` = 0\n<strong>AND<\/strong> `teacher`.`etat_teacher` = &#039;actif&#039;","trace":[{"file":"SYSTEMPATH\/Database\/BaseBuilder.php:1616","function":"\u00a0\u00a0\u00a0\u00a0\u00a0\u00a0\u00a0\u00a0CodeIgniter\\Database\\BaseConnection->query()","index":"\u00a0\u00a01\u00a0\u00a0\u00a0\u00a0"},{"file":"APPPATH\/Models\/TeacherModel.php:389","function":"\u00a0\u00a0\u00a0\u00a0\u00a0\u00a0\u00a0\u00a0CodeIgniter\\Database\\BaseBuilder->get()","index":"\u00a0\u00a02\u00a0\u00a0\u00a0\u00a0"},{"file":"APPPATH\/Controllers\/StatistiqueController.php:46","function":"\u00a0\u00a0\u00a0\u00a0\u00a0\u00a0\u00a0\u00a0App\\Models\\TeacherModel->getAllTeacherYear()","index":"\u00a0\u00a03\u00a0\u00a0\u00a0\u00a0"},{"file":"SYSTEMPATH\/CodeIgniter.php:932","function":"\u00a0\u00a0\u00a0\u00a0\u00a0\u00a0\u00a0\u00a0App\\Controllers\\StatistiqueController->statistique1()","index":"\u00a0\u00a04\u00a0\u00a0\u00a0\u00a0"},{"file":"SYSTEMPATH\/CodeIgniter.php:497","function":"\u00a0\u00a0\u00a0\u00a0\u00a0\u00a0\u00a0\u00a0CodeIgniter\\CodeIgniter->runController()","index":"\u00a0\u00a05\u00a0\u00a0\u00a0\u00a0"},{"file":"SYSTEMPATH\/CodeIgniter.php:366","function":"\u00a0\u00a0\u00a0\u00a0\u00a0\u00a0\u00a0\u00a0CodeIgniter\\CodeIgniter->handleRequest()","index":"\u00a0\u00a06\u00a0\u00a0\u00a0\u00a0"},{"file":"FCPATH\/index.php:67","function":"\u00a0\u00a0\u00a0\u00a0\u00a0\u00a0\u00a0\u00a0CodeIgniter\\CodeIgniter->run()","index":"\u00a0\u00a07\u00a0\u00a0\u00a0\u00a0"},{"file":"SYSTEMPATH\/Commands\/Server\/rewrite.php:47","args":["\/home\/takam\/Bureau\/ecole-negou-new\/public\/index.php"],"function":"\u00a0\u00a0\u00a0\u00a0\u00a0\u00a0\u00a0\u00a0require_once()","index":"\u00a0\u00a08\u00a0\u00a0\u00a0\u00a0"}],"trace-file":"APPPATH\/Models\/TeacherModel.php:389","qid":"c02fc52248879922aee839a5d09ce2bd"},{"hover":"","class":"","duration":"0.32 ms","sql":"<strong>SELECT<\/strong> `teacher`.`matricule`, `teacher`.`name`, `teacher`.`surname`, `teacher`.`diplome`, `teacher`.`login`, `teacher`.`photo`, `teacher`.`tel`, `teacher`.`sexe`, `teacher`.`email`\n<strong>FROM<\/strong> `teacher`\n<strong>INNER<\/strong> <strong>JOIN<\/strong> `year` <strong>ON<\/strong> `year`.`year_id`=`teacher`.`year_id`\n<strong>INNER<\/strong> <strong>JOIN<\/strong> `teacher_class` <strong>ON<\/strong> `teacher_class`.`teacher_id`=`teacher`.`teacher_id`\n<strong>INNER<\/strong> <strong>JOIN<\/strong> `class` <strong>ON<\/strong> `class`.`class_id`=`teacher_class`.`class_id`\n<strong>WHERE<\/strong> `teacher_class`.`year_id` = 1\n<strong>AND<\/strong> `teacher_class`.`status_teacher_class` = 0\n<strong>AND<\/strong> `teacher_class`.`etat_teacher_class` = &#039;actif&#039;\n<strong>AND<\/strong> `teacher`.`status_teacher` = 0\n<strong>AND<\/strong> `teacher`.`etat_teacher` = &#039;actif&#039;\n<strong>AND<\/strong> `teacher`.`connected` = &#039;true&#039;","trace":[{"file":"SYSTEMPATH\/Database\/BaseBuilder.php:1616","function":"\u00a0\u00a0\u00a0\u00a0\u00a0\u00a0\u00a0\u00a0CodeIgniter\\Database\\BaseConnection->query()","index":"\u00a0\u00a01\u00a0\u00a0\u00a0\u00a0"},{"file":"APPPATH\/Models\/TeacherModel.php:324","function":"\u00a0\u00a0\u00a0\u00a0\u00a0\u00a0\u00a0\u00a0CodeIgniter\\Database\\BaseBuilder->get()","index":"\u00a0\u00a02\u00a0\u00a0\u00a0\u00a0"},{"file":"APPPATH\/Controllers\/StatistiqueController.php:47","function":"\u00a0\u00a0\u00a0\u00a0\u00a0\u00a0\u00a0\u00a0App\\Models\\TeacherModel->getAllConnected()","index":"\u00a0\u00a03\u00a0\u00a0\u00a0\u00a0"},{"file":"SYSTEMPATH\/CodeIgniter.php:932","function":"\u00a0\u00a0\u00a0\u00a0\u00a0\u00a0\u00a0\u00a0App\\Controllers\\StatistiqueController->statistique1()","index":"\u00a0\u00a04\u00a0\u00a0\u00a0\u00a0"},{"file":"SYSTEMPATH\/CodeIgniter.php:497","function":"\u00a0\u00a0\u00a0\u00a0\u00a0\u00a0\u00a0\u00a0CodeIgniter\\CodeIgniter->runController()","index":"\u00a0\u00a05\u00a0\u00a0\u00a0\u00a0"},{"file":"SYSTEMPATH\/CodeIgniter.php:366","function":"\u00a0\u00a0\u00a0\u00a0\u00a0\u00a0\u00a0\u00a0CodeIgniter\\CodeIgniter->handleRequest()","index":"\u00a0\u00a06\u00a0\u00a0\u00a0\u00a0"},{"file":"FCPATH\/index.php:67","function":"\u00a0\u00a0\u00a0\u00a0\u00a0\u00a0\u00a0\u00a0CodeIgniter\\CodeIgniter->run()","index":"\u00a0\u00a07\u00a0\u00a0\u00a0\u00a0"},{"file":"SYSTEMPATH\/Commands\/Server\/rewrite.php:47","args":["\/home\/takam\/Bureau\/ecole-negou-new\/public\/index.php"],"function":"\u00a0\u00a0\u00a0\u00a0\u00a0\u00a0\u00a0\u00a0require_once()","index":"\u00a0\u00a08\u00a0\u00a0\u00a0\u00a0"}],"trace-file":"APPPATH\/Models\/TeacherModel.php:324","qid":"4e274ede0a383cbb87c438315adde38d"},{"hover":"","class":"","duration":"0.23 ms","sql":"<strong>SELECT<\/strong> *\n<strong>FROM<\/strong> `student`\n<strong>WHERE<\/strong> `status_student` = 0\n<strong>AND<\/strong> `etat_student` = &#039;actif&#039;","trace":[{"file":"SYSTEMPATH\/Database\/BaseBuilder.php:1616","function":"\u00a0\u00a0\u00a0\u00a0\u00a0\u00a0\u00a0\u00a0CodeIgniter\\Database\\BaseConnection->query()","index":"\u00a0\u00a01\u00a0\u00a0\u00a0\u00a0"},{"file":"APPPATH\/Models\/StudentModel.php:97","function":"\u00a0\u00a0\u00a0\u00a0\u00a0\u00a0\u00a0\u00a0CodeIgniter\\Database\\BaseBuilder->get()","index":"\u00a0\u00a02\u00a0\u00a0\u00a0\u00a0"},{"file":"APPPATH\/Controllers\/StatistiqueController.php:48","function":"\u00a0\u00a0\u00a0\u00a0\u00a0\u00a0\u00a0\u00a0App\\Models\\StudentModel->getAllStudent()","index":"\u00a0\u00a03\u00a0\u00a0\u00a0\u00a0"},{"file":"SYSTEMPATH\/CodeIgniter.php:932","function":"\u00a0\u00a0\u00a0\u00a0\u00a0\u00a0\u00a0\u00a0App\\Controllers\\StatistiqueController->statistique1()","index":"\u00a0\u00a04\u00a0\u00a0\u00a0\u00a0"},{"file":"SYSTEMPATH\/CodeIgniter.php:497","function":"\u00a0\u00a0\u00a0\u00a0\u00a0\u00a0\u00a0\u00a0CodeIgniter\\CodeIgniter->runController()","index":"\u00a0\u00a05\u00a0\u00a0\u00a0\u00a0"},{"file":"SYSTEMPATH\/CodeIgniter.php:366","function":"\u00a0\u00a0\u00a0\u00a0\u00a0\u00a0\u00a0\u00a0CodeIgniter\\CodeIgniter->handleRequest()","index":"\u00a0\u00a06\u00a0\u00a0\u00a0\u00a0"},{"file":"FCPATH\/index.php:67","function":"\u00a0\u00a0\u00a0\u00a0\u00a0\u00a0\u00a0\u00a0CodeIgniter\\CodeIgniter->run()","index":"\u00a0\u00a07\u00a0\u00a0\u00a0\u00a0"},{"file":"SYSTEMPATH\/Commands\/Server\/rewrite.php:47","args":["\/home\/takam\/Bureau\/ecole-negou-new\/public\/index.php"],"function":"\u00a0\u00a0\u00a0\u00a0\u00a0\u00a0\u00a0\u00a0require_once()","index":"\u00a0\u00a08\u00a0\u00a0\u00a0\u00a0"}],"trace-file":"APPPATH\/Models\/StudentModel.php:97","qid":"44ca9b5da7242bff61f7a70aa2a69f48"},{"hover":"","class":"","duration":"0.25 ms","sql":"<strong>SELECT<\/strong> *\n<strong>FROM<\/strong> `school`\n<strong>WHERE<\/strong> `status_school` = 0\n<strong>AND<\/strong> `etat_school` = &#039;actif&#039;\n<strong>ORDER<\/strong> <strong>BY<\/strong> `name` <strong>ASC<\/strong>","trace":[{"file":"SYSTEMPATH\/Database\/BaseBuilder.php:1616","function":"\u00a0\u00a0\u00a0\u00a0\u00a0\u00a0\u00a0\u00a0CodeIgniter\\Database\\BaseConnection->query()","index":"\u00a0\u00a01\u00a0\u00a0\u00a0\u00a0"},{"file":"APPPATH\/Models\/SchoolModel.php:164","function":"\u00a0\u00a0\u00a0\u00a0\u00a0\u00a0\u00a0\u00a0CodeIgniter\\Database\\BaseBuilder->get()","index":"\u00a0\u00a02\u00a0\u00a0\u00a0\u00a0"},{"file":"APPPATH\/Controllers\/StatistiqueController.php:49","function":"\u00a0\u00a0\u00a0\u00a0\u00a0\u00a0\u00a0\u00a0App\\Models\\SchoolModel->findAllSchool()","index":"\u00a0\u00a03\u00a0\u00a0\u00a0\u00a0"},{"file":"SYSTEMPATH\/CodeIgniter.php:932","function":"\u00a0\u00a0\u00a0\u00a0\u00a0\u00a0\u00a0\u00a0App\\Controllers\\StatistiqueController->statistique1()","index":"\u00a0\u00a04\u00a0\u00a0\u00a0\u00a0"},{"file":"SYSTEMPATH\/CodeIgniter.php:497","function":"\u00a0\u00a0\u00a0\u00a0\u00a0\u00a0\u00a0\u00a0CodeIgniter\\CodeIgniter->runController()","index":"\u00a0\u00a05\u00a0\u00a0\u00a0\u00a0"},{"file":"SYSTEMPATH\/CodeIgniter.php:366","function":"\u00a0\u00a0\u00a0\u00a0\u00a0\u00a0\u00a0\u00a0CodeIgniter\\CodeIgniter->handleRequest()","index":"\u00a0\u00a06\u00a0\u00a0\u00a0\u00a0"},{"file":"FCPATH\/index.php:67","function":"\u00a0\u00a0\u00a0\u00a0\u00a0\u00a0\u00a0\u00a0CodeIgniter\\CodeIgniter->run()","index":"\u00a0\u00a07\u00a0\u00a0\u00a0\u00a0"},{"file":"SYSTEMPATH\/Commands\/Server\/rewrite.php:47","args":["\/home\/takam\/Bureau\/ecole-negou-new\/public\/index.php"],"function":"\u00a0\u00a0\u00a0\u00a0\u00a0\u00a0\u00a0\u00a0require_once()","index":"\u00a0\u00a08\u00a0\u00a0\u00a0\u00a0"}],"trace-file":"APPPATH\/Models\/SchoolModel.php:164","qid":"6080765c827611481a9ce79a214fd793"},{"hover":"","class":"","duration":"0.42 ms","sql":"<strong>SELECT<\/strong> <strong>SUM<\/strong>(salaire.montant) as total\n<strong>FROM<\/strong> `salaire`\n<strong>INNER<\/strong> <strong>JOIN<\/strong> `teacher` <strong>ON<\/strong> `teacher`.`teacher_id` = `salaire`.`teacher_id`\n<strong>INNER<\/strong> <strong>JOIN<\/strong> `teacher_school` <strong>ON<\/strong> `teacher_school`.`teacher_id` = `teacher`.`teacher_id`\n<strong>INNER<\/strong> <strong>JOIN<\/strong> `school` <strong>ON<\/strong> `school`.`school_id` = `teacher_school`.`school_id`\n<strong>INNER<\/strong> <strong>JOIN<\/strong> `year` <strong>ON<\/strong> `year`.`year_id` = `salaire`.`year_id`\n<strong>WHERE<\/strong> `teacher`.`year_id` = 1\n<strong>AND<\/strong> `teacher`.`status_teacher` = 0\n<strong>AND<\/strong> `teacher`.`etat_teacher` = &#039;actif&#039;\n<strong>AND<\/strong> `teacher_school`.`status_teacher_school` = 0\n<strong>AND<\/strong> `teacher_school`.`etat_teacher_school` = &#039;actif&#039;\n<strong>AND<\/strong> `school`.`status_school` = 0\n<strong>AND<\/strong> `school`.`etat_school` = &#039;actif&#039;\n<strong>AND<\/strong> `salaire`.`status_salaire` = 0\n<strong>AND<\/strong> `salaire`.`etat_salaire` = &#039;actif&#039;","trace":[{"file":"SYSTEMPATH\/Database\/BaseBuilder.php:1616","function":"\u00a0\u00a0\u00a0\u00a0\u00a0\u00a0\u00a0\u00a0CodeIgniter\\Database\\BaseConnection->query()","index":"\u00a0\u00a01\u00a0\u00a0\u00a0\u00a0"},{"file":"APPPATH\/Models\/SalaireModel.php:104","function":"\u00a0\u00a0\u00a0\u00a0\u00a0\u00a0\u00a0\u00a0CodeIgniter\\Database\\BaseBuilder->get()","index":"\u00a0\u00a02\u00a0\u00a0\u00a0\u00a0"},{"file":"APPPATH\/Controllers\/StatistiqueController.php:50","function":"\u00a0\u00a0\u00a0\u00a0\u00a0\u00a0\u00a0\u00a0App\\Models\\SalaireModel->getSumAllSalaireShool()","index":"\u00a0\u00a03\u00a0\u00a0\u00a0\u00a0"},{"file":"SYSTEMPATH\/CodeIgniter.php:932","function":"\u00a0\u00a0\u00a0\u00a0\u00a0\u00a0\u00a0\u00a0App\\Controllers\\StatistiqueController->statistique1()","index":"\u00a0\u00a04\u00a0\u00a0\u00a0\u00a0"},{"file":"SYSTEMPATH\/CodeIgniter.php:497","function":"\u00a0\u00a0\u00a0\u00a0\u00a0\u00a0\u00a0\u00a0CodeIgniter\\CodeIgniter->runController()","index":"\u00a0\u00a05\u00a0\u00a0\u00a0\u00a0"},{"file":"SYSTEMPATH\/CodeIgniter.php:366","function":"\u00a0\u00a0\u00a0\u00a0\u00a0\u00a0\u00a0\u00a0CodeIgniter\\CodeIgniter->handleRequest()","index":"\u00a0\u00a06\u00a0\u00a0\u00a0\u00a0"},{"file":"FCPATH\/index.php:67","function":"\u00a0\u00a0\u00a0\u00a0\u00a0\u00a0\u00a0\u00a0CodeIgniter\\CodeIgniter->run()","index":"\u00a0\u00a07\u00a0\u00a0\u00a0\u00a0"},{"file":"SYSTEMPATH\/Commands\/Server\/rewrite.php:47","args":["\/home\/takam\/Bureau\/ecole-negou-new\/public\/index.php"],"function":"\u00a0\u00a0\u00a0\u00a0\u00a0\u00a0\u00a0\u00a0require_once()","index":"\u00a0\u00a08\u00a0\u00a0\u00a0\u00a0"}],"trace-file":"APPPATH\/Models\/SalaireModel.php:104","qid":"7ac373504cbc7f4c18d6ac0a892410ec"}]},"badgeValue":6,"isEmpty":false,"hasTabContent":true,"hasLabel":false,"icon":"data:image\/png;base64,iVBORw0KGgoAAAANSUhEUgAAABgAAAAYCAYAAADgdz34AAAAAXNSR0IArs4c6QAAAARnQU1BAACxjwv8YQUAAAAJcEhZcwAADsMAAA7DAcdvqGQAAADMSURBVEhLY6A3YExLSwsA4nIycQDIDIhRWEBqamo\/UNF\/SjDQjF6ocZgAKPkRiFeEhoYyQ4WIBiA9QAuWAPEHqBAmgLqgHcolGQD1V4DMgHIxwbCxYD+QBqcKINseKo6eWrBioPrtQBq\/BcgY5ht0cUIYbBg2AJKkRxCNWkDQgtFUNJwtABr+F6igE8olGQD114HMgHIxAVDyAhA\/AlpSA8RYUwoeXAPVex5qHCbIyMgwBCkAuQJIY00huDBUz\/mUlBQDqHGjgBjAwAAACexpph6oHSQAAAAASUVORK5CYII=","hasTimelineData":true,"timelineData":[{"name":"Connecting to Database: \"default\"","component":"Database","start":1733841109.241284,"duration":"0.000251"},{"name":"Query","component":"Database","start":1733841109.241596,"duration":"0.001469","query":"<strong>SELECT<\/strong> *\n<strong>FROM<\/strong> `year`\n<strong>WHERE<\/strong> `status_year` = 0\n<strong>AND<\/strong> `etat_year` = &#039;actif&#039;"},{"name":"Query","component":"Database","start":1733841109.243687,"duration":"0.000361","query":"<strong>SELECT<\/strong> `teacher`.`matricule`, `teacher`.`name`, `teacher`.`surname`, `teacher`.`diplome`, `teacher`.`login`, `teacher`.`photo`, `teacher`.`tel`, `teacher`.`sexe`, `teacher`.`email`\n<strong>FROM<\/strong> `teacher`\n<strong>INNER<\/strong> <strong>JOIN<\/strong> `year` <strong>ON<\/strong> `year`.`year_id`=`teacher`.`year_id`\n<strong>WHERE<\/strong> `teacher`.`year_id` = 1\n<strong>AND<\/strong> `teacher`.`status_teacher` = 0\n<strong>AND<\/strong> `teacher`.`etat_teacher` = &#039;actif&#039;"},{"name":"Query","component":"Database","start":1733841109.244683,"duration":"0.000321","query":"<strong>SELECT<\/strong> `teacher`.`matricule`, `teacher`.`name`, `teacher`.`surname`, `teacher`.`diplome`, `teacher`.`login`, `teacher`.`photo`, `teacher`.`tel`, `teacher`.`sexe`, `teacher`.`email`\n<strong>FROM<\/strong> `teacher`\n<strong>INNER<\/strong> <strong>JOIN<\/strong> `year` <strong>ON<\/strong> `year`.`year_id`=`teacher`.`year_id`\n<strong>INNER<\/strong> <strong>JOIN<\/strong> `teacher_class` <strong>ON<\/strong> `teacher_class`.`teacher_id`=`teacher`.`teacher_id`\n<strong>INNER<\/strong> <strong>JOIN<\/strong> `class` <strong>ON<\/strong> `class`.`class_id`=`teacher_class`.`class_id`\n<strong>WHERE<\/strong> `teacher_class`.`year_id` = 1\n<strong>AND<\/strong> `teacher_class`.`status_teacher_class` = 0\n<strong>AND<\/strong> `teacher_class`.`etat_teacher_class` = &#039;actif&#039;\n<strong>AND<\/strong> `teacher`.`status_teacher` = 0\n<strong>AND<\/strong> `teacher`.`etat_teacher` = &#039;actif&#039;\n<strong>AND<\/strong> `teacher`.`connected` = &#039;true&#039;"},{"name":"Query","component":"Database","start":1733841109.245297,"duration":"0.000226","query":"<strong>SELECT<\/strong> *\n<strong>FROM<\/strong> `student`\n<strong>WHERE<\/strong> `status_student` = 0\n<strong>AND<\/strong> `etat_student` = &#039;actif&#039;"},{"name":"Query","component":"Database","start":1733841109.250112,"duration":"0.000252","query":"<strong>SELECT<\/strong> *\n<strong>FROM<\/strong> `school`\n<strong>WHERE<\/strong> `status_school` = 0\n<strong>AND<\/strong> `etat_school` = &#039;actif&#039;\n<strong>ORDER<\/strong> <strong>BY<\/strong> `name` <strong>ASC<\/strong>"},{"name":"Query","component":"Database","start":1733841109.250989,"duration":"0.000423","query":"<strong>SELECT<\/strong> <strong>SUM<\/strong>(salaire.montant) as total\n<strong>FROM<\/strong> `salaire`\n<strong>INNER<\/strong> <strong>JOIN<\/strong> `teacher` <strong>ON<\/strong> `teacher`.`teacher_id` = `salaire`.`teacher_id`\n<strong>INNER<\/strong> <strong>JOIN<\/strong> `teacher_school` <strong>ON<\/strong> `teacher_school`.`teacher_id` = `teacher`.`teacher_id`\n<strong>INNER<\/strong> <strong>JOIN<\/strong> `school` <strong>ON<\/strong> `school`.`school_id` = `teacher_school`.`school_id`\n<strong>INNER<\/strong> <strong>JOIN<\/strong> `year` <strong>ON<\/strong> `year`.`year_id` = `salaire`.`year_id`\n<strong>WHERE<\/strong> `teacher`.`year_id` = 1\n<strong>AND<\/strong> `teacher`.`status_teacher` = 0\n<strong>AND<\/strong> `teacher`.`etat_teacher` = &#039;actif&#039;\n<strong>AND<\/strong> `teacher_school`.`status_teacher_school` = 0\n<strong>AND<\/strong> `teacher_school`.`etat_teacher_school` = &#039;actif&#039;\n<strong>AND<\/strong> `school`.`status_school` = 0\n<strong>AND<\/strong> `school`.`etat_school` = &#039;actif&#039;\n<strong>AND<\/strong> `salaire`.`status_salaire` = 0\n<strong>AND<\/strong> `salaire`.`etat_salaire` = &#039;actif&#039;"}]},{"title":"Logs","titleSafe":"logs","titleDetails":"","display":{"logs":[]},"badgeValue":null,"isEmpty":true,"hasTabContent":true,"hasLabel":false,"icon":"data:image\/png;base64,iVBORw0KGgoAAAANSUhEUgAAABgAAAAYCAYAAADgdz34AAAAAXNSR0IArs4c6QAAAARnQU1BAACxjwv8YQUAAAAJcEhZcwAADsMAAA7DAcdvqGQAAACYSURBVEhLYxgFJIHU1FSjtLS0i0D8AYj7gEKMEBkqAaAFF4D4ERCvAFrwH4gDoFIMKSkpFkB+OTEYqgUTACXfA\/GqjIwMQyD9H2hRHlQKJFcBEiMGQ7VgAqCBvUgK32dmZspCpagGGNPT0\/1BLqeF4bQHQJePpiIwhmrBBEADR1MRfgB0+WgqAmOoFkwANHA0FY0CUgEDAwCQ0PUpNB3kqwAAAABJRU5ErkJggg==","hasTimelineData":false,"timelineData":[]},{"title":"Views","titleSafe":"views","titleDetails":"","display":[],"badgeValue":0,"isEmpty":false,"hasTabContent":false,"hasLabel":true,"icon":"data:image\/png;base64,iVBORw0KGgoAAAANSUhEUgAAABgAAAAYCAYAAADgdz34AAAAAXNSR0IArs4c6QAAAARnQU1BAACxjwv8YQUAAAAJcEhZcwAADsMAAA7DAcdvqGQAAADeSURBVEhL7ZSxDcIwEEWNYA0YgGmgyAaJLTcUaaBzQQEVjMEabBQxAdw53zTHiThEovGTfnE\/9rsoRUxhKLOmaa6Uh7X2+UvguLCzVxN1XW9x4EYHzik033Hp3X0LO+DaQG8MDQcuq6qao4qkHuMgQggLvkPLjqh00ZgFDBacMJYFkuwFlH1mshdkZ5JPJERA9JpI6xNCBESvibQ+IURA9JpI6xNCBESvibQ+IURA9DTsuHTOrVFFxixgB\/eUFlU8uKJ0eDBFOu\/9EvoeKnlJS2\/08Tc8NOwQ8sIfMeYFjqKDjdU2sp4AAAAASUVORK5CYII=","hasTimelineData":true,"timelineData":[]},{"title":"Files","titleSafe":"files","titleDetails":"( 149 )","display":{"coreFiles":[{"name":"AbstractRenderer.php","path":"SYSTEMPATH\/ThirdParty\/Kint\/Renderer\/AbstractRenderer.php"},{"name":"AutoloadConfig.php","path":"SYSTEMPATH\/Config\/AutoloadConfig.php"},{"name":"Autoloader.php","path":"SYSTEMPATH\/Autoloader\/Autoloader.php"},{"name":"BaseBuilder.php","path":"SYSTEMPATH\/Database\/BaseBuilder.php"},{"name":"BaseCollector.php","path":"SYSTEMPATH\/Debug\/Toolbar\/Collectors\/BaseCollector.php"},{"name":"BaseConfig.php","path":"SYSTEMPATH\/Config\/BaseConfig.php"},{"name":"BaseConnection.php","path":"SYSTEMPATH\/Database\/BaseConnection.php"},{"name":"BaseHandler.php","path":"SYSTEMPATH\/Cache\/Handlers\/BaseHandler.php"},{"name":"BaseModel.php","path":"SYSTEMPATH\/BaseModel.php"},{"name":"BaseResource.php","path":"SYSTEMPATH\/RESTful\/BaseResource.php"},{"name":"BaseResult.php","path":"SYSTEMPATH\/Database\/BaseResult.php"},{"name":"BaseService.php","path":"SYSTEMPATH\/Config\/BaseService.php"},{"name":"Builder.php","path":"SYSTEMPATH\/Database\/SQLite3\/Builder.php"},{"name":"CacheFactory.php","path":"SYSTEMPATH\/Cache\/CacheFactory.php"},{"name":"CacheInterface.php","path":"SYSTEMPATH\/Cache\/CacheInterface.php"},{"name":"CliRenderer.php","path":"SYSTEMPATH\/ThirdParty\/Kint\/Renderer\/CliRenderer.php"},{"name":"CloneableCookieInterface.php","path":"SYSTEMPATH\/Cookie\/CloneableCookieInterface.php"},{"name":"CodeIgniter.php","path":"SYSTEMPATH\/CodeIgniter.php"},{"name":"Common.php","path":"SYSTEMPATH\/Common.php"},{"name":"ConditionalTrait.php","path":"SYSTEMPATH\/Traits\/ConditionalTrait.php"},{"name":"Config.php","path":"SYSTEMPATH\/Database\/Config.php"},{"name":"Connection.php","path":"SYSTEMPATH\/Database\/SQLite3\/Connection.php"},{"name":"ConnectionInterface.php","path":"SYSTEMPATH\/Database\/ConnectionInterface.php"},{"name":"ContentSecurityPolicy.php","path":"SYSTEMPATH\/HTTP\/ContentSecurityPolicy.php"},{"name":"Controller.php","path":"SYSTEMPATH\/Controller.php"},{"name":"Cookie.php","path":"SYSTEMPATH\/Cookie\/Cookie.php"},{"name":"CookieInterface.php","path":"SYSTEMPATH\/Cookie\/CookieInterface.php"},{"name":"CookieStore.php","path":"SYSTEMPATH\/Cookie\/CookieStore.php"},{"name":"Database.php","path":"SYSTEMPATH\/Database\/Database.php"},{"name":"Database.php","path":"SYSTEMPATH\/Debug\/Toolbar\/Collectors\/Database.php"},{"name":"DebugToolbar.php","path":"SYSTEMPATH\/Filters\/DebugToolbar.php"},{"name":"DotEnv.php","path":"SYSTEMPATH\/Config\/DotEnv.php"},{"name":"Events.php","path":"SYSTEMPATH\/Debug\/Toolbar\/Collectors\/Events.php"},{"name":"Events.php","path":"SYSTEMPATH\/Events\/Events.php"},{"name":"Exceptions.php","path":"SYSTEMPATH\/Debug\/Exceptions.php"},{"name":"FacadeInterface.php","path":"SYSTEMPATH\/ThirdParty\/Kint\/FacadeInterface.php"},{"name":"Factories.php","path":"SYSTEMPATH\/Config\/Factories.php"},{"name":"Factory.php","path":"SYSTEMPATH\/Config\/Factory.php"},{"name":"FileHandler.php","path":"SYSTEMPATH\/Cache\/Handlers\/FileHandler.php"},{"name":"FileLocator.php","path":"SYSTEMPATH\/Autoloader\/FileLocator.php"},{"name":"Files.php","path":"SYSTEMPATH\/Debug\/Toolbar\/Collectors\/Files.php"},{"name":"FilterInterface.php","path":"SYSTEMPATH\/Filters\/FilterInterface.php"},{"name":"Filters.php","path":"SYSTEMPATH\/Filters\/Filters.php"},{"name":"Format.php","path":"SYSTEMPATH\/Format\/Format.php"},{"name":"FormatterInterface.php","path":"SYSTEMPATH\/Format\/FormatterInterface.php"},{"name":"Header.php","path":"SYSTEMPATH\/HTTP\/Header.php"},{"name":"IncomingRequest.php","path":"SYSTEMPATH\/HTTP\/IncomingRequest.php"},{"name":"JSONFormatter.php","path":"SYSTEMPATH\/Format\/JSONFormatter.php"},{"name":"Kint.php","path":"SYSTEMPATH\/ThirdParty\/Kint\/Kint.php"},{"name":"Logger.php","path":"SYSTEMPATH\/Log\/Logger.php"},{"name":"Logs.php","path":"SYSTEMPATH\/Debug\/Toolbar\/Collectors\/Logs.php"},{"name":"Message.php","path":"SYSTEMPATH\/HTTP\/Message.php"},{"name":"MessageInterface.php","path":"SYSTEMPATH\/HTTP\/MessageInterface.php"},{"name":"MessageTrait.php","path":"SYSTEMPATH\/HTTP\/MessageTrait.php"},{"name":"Model.php","path":"SYSTEMPATH\/Model.php"},{"name":"Modules.php","path":"SYSTEMPATH\/Modules\/Modules.php"},{"name":"OutgoingRequest.php","path":"SYSTEMPATH\/HTTP\/OutgoingRequest.php"},{"name":"OutgoingRequestInterface.php","path":"SYSTEMPATH\/HTTP\/OutgoingRequestInterface.php"},{"name":"Query.php","path":"SYSTEMPATH\/Database\/Query.php"},{"name":"QueryInterface.php","path":"SYSTEMPATH\/Database\/QueryInterface.php"},{"name":"RendererInterface.php","path":"SYSTEMPATH\/ThirdParty\/Kint\/Renderer\/RendererInterface.php"},{"name":"RendererInterface.php","path":"SYSTEMPATH\/View\/RendererInterface.php"},{"name":"Request.php","path":"SYSTEMPATH\/HTTP\/Request.php"},{"name":"RequestInterface.php","path":"SYSTEMPATH\/HTTP\/RequestInterface.php"},{"name":"RequestTrait.php","path":"SYSTEMPATH\/HTTP\/RequestTrait.php"},{"name":"ResourcePresenter.php","path":"SYSTEMPATH\/RESTful\/ResourcePresenter.php"},{"name":"Response.php","path":"SYSTEMPATH\/HTTP\/Response.php"},{"name":"ResponseInterface.php","path":"SYSTEMPATH\/HTTP\/ResponseInterface.php"},{"name":"ResponseTrait.php","path":"SYSTEMPATH\/API\/ResponseTrait.php"},{"name":"ResponseTrait.php","path":"SYSTEMPATH\/HTTP\/ResponseTrait.php"},{"name":"Result.php","path":"SYSTEMPATH\/Database\/SQLite3\/Result.php"},{"name":"ResultInterface.php","path":"SYSTEMPATH\/Database\/ResultInterface.php"},{"name":"RichRenderer.php","path":"SYSTEMPATH\/ThirdParty\/Kint\/Renderer\/RichRenderer.php"},{"name":"RouteCollection.php","path":"SYSTEMPATH\/Router\/RouteCollection.php"},{"name":"RouteCollectionInterface.php","path":"SYSTEMPATH\/Router\/RouteCollectionInterface.php"},{"name":"Router.php","path":"SYSTEMPATH\/Router\/Router.php"},{"name":"RouterInterface.php","path":"SYSTEMPATH\/Router\/RouterInterface.php"},{"name":"Routes.php","path":"SYSTEMPATH\/Debug\/Toolbar\/Collectors\/Routes.php"},{"name":"Services.php","path":"SYSTEMPATH\/Config\/Services.php"},{"name":"TextRenderer.php","path":"SYSTEMPATH\/ThirdParty\/Kint\/Renderer\/TextRenderer.php"},{"name":"Time.php","path":"SYSTEMPATH\/I18n\/Time.php"},{"name":"TimeTrait.php","path":"SYSTEMPATH\/I18n\/TimeTrait.php"},{"name":"Timer.php","path":"SYSTEMPATH\/Debug\/Timer.php"},{"name":"Timers.php","path":"SYSTEMPATH\/Debug\/Toolbar\/Collectors\/Timers.php"},{"name":"Toolbar.php","path":"SYSTEMPATH\/Debug\/Toolbar.php"},{"name":"URI.php","path":"SYSTEMPATH\/HTTP\/URI.php"},{"name":"UserAgent.php","path":"SYSTEMPATH\/HTTP\/UserAgent.php"},{"name":"Utils.php","path":"SYSTEMPATH\/ThirdParty\/Kint\/Utils.php"},{"name":"Validation.php","path":"SYSTEMPATH\/Validation\/Validation.php"},{"name":"ValidationInterface.php","path":"SYSTEMPATH\/Validation\/ValidationInterface.php"},{"name":"View.php","path":"SYSTEMPATH\/Config\/View.php"},{"name":"View.php","path":"SYSTEMPATH\/View\/View.php"},{"name":"ViewDecoratorTrait.php","path":"SYSTEMPATH\/View\/ViewDecoratorTrait.php"},{"name":"Views.php","path":"SYSTEMPATH\/Debug\/Toolbar\/Collectors\/Views.php"},{"name":"array_helper.php","path":"SYSTEMPATH\/Helpers\/array_helper.php"},{"name":"bootstrap.php","path":"SYSTEMPATH\/bootstrap.php"},{"name":"init.php","path":"SYSTEMPATH\/ThirdParty\/Kint\/init.php"},{"name":"init_helpers.php","path":"SYSTEMPATH\/ThirdParty\/Kint\/init_helpers.php"},{"name":"kint_helper.php","path":"SYSTEMPATH\/Helpers\/kint_helper.php"},{"name":"rewrite.php","path":"SYSTEMPATH\/Commands\/Server\/rewrite.php"},{"name":"url_helper.php","path":"SYSTEMPATH\/Helpers\/url_helper.php"}],"userFiles":[{"name":"App.php","path":"APPPATH\/Config\/App.php"},{"name":"Autoload.php","path":"APPPATH\/Config\/Autoload.php"},{"name":"BaseController.php","path":"APPPATH\/Controllers\/BaseController.php"},{"name":"Cache.php","path":"APPPATH\/Config\/Cache.php"},{"name":"ClassLoader.php","path":"VENDORPATH\/composer\/ClassLoader.php"},{"name":"Common.php","path":"APPPATH\/Common.php"},{"name":"Constants.php","path":"APPPATH\/Config\/Constants.php"},{"name":"ContentSecurityPolicy.php","path":"APPPATH\/Config\/ContentSecurityPolicy.php"},{"name":"Cookie.php","path":"APPPATH\/Config\/Cookie.php"},{"name":"Database.php","path":"APPPATH\/Config\/Database.php"},{"name":"Escaper.php","path":"VENDORPATH\/laminas\/laminas-escaper\/src\/Escaper.php"},{"name":"Events.php","path":"APPPATH\/Config\/Events.php"},{"name":"Exceptions.php","path":"APPPATH\/Config\/Exceptions.php"},{"name":"Feature.php","path":"APPPATH\/Config\/Feature.php"},{"name":"Filters.php","path":"APPPATH\/Config\/Filters.php"},{"name":"Format.php","path":"APPPATH\/Config\/Format.php"},{"name":"Functions.php","path":"VENDORPATH\/phpunit\/phpunit\/src\/Framework\/Assert\/Functions.php"},{"name":"HTMLPurifier.composer.php","path":"VENDORPATH\/ezyang\/htmlpurifier\/library\/HTMLPurifier.composer.php"},{"name":"HistorySession.php","path":"APPPATH\/Controllers\/History\/HistorySession.php"},{"name":"InstalledVersions.php","path":"VENDORPATH\/composer\/InstalledVersions.php"},{"name":"Kint.php","path":"APPPATH\/Config\/Kint.php"},{"name":"LogLevel.php","path":"VENDORPATH\/psr\/log\/Psr\/Log\/LogLevel.php"},{"name":"Logger.php","path":"APPPATH\/Config\/Logger.php"},{"name":"LoggerInterface.php","path":"VENDORPATH\/psr\/log\/Psr\/Log\/LoggerInterface.php"},{"name":"Modules.php","path":"APPPATH\/Config\/Modules.php"},{"name":"Paths.php","path":"APPPATH\/Config\/Paths.php"},{"name":"Routes.php","path":"APPPATH\/Config\/Routes.php"},{"name":"SalaireModel.php","path":"APPPATH\/Models\/SalaireModel.php"},{"name":"SchoolModel.php","path":"APPPATH\/Models\/SchoolModel.php"},{"name":"Services.php","path":"APPPATH\/Config\/Services.php"},{"name":"StatistiqueController.php","path":"APPPATH\/Controllers\/StatistiqueController.php"},{"name":"StudentModel.php","path":"APPPATH\/Models\/StudentModel.php"},{"name":"TeacherModel.php","path":"APPPATH\/Models\/TeacherModel.php"},{"name":"Toolbar.php","path":"APPPATH\/Config\/Toolbar.php"},{"name":"UserAgents.php","path":"APPPATH\/Config\/UserAgents.php"},{"name":"UserModel.php","path":"APPPATH\/Models\/UserModel.php"},{"name":"Validation.php","path":"APPPATH\/Config\/Validation.php"},{"name":"View.php","path":"APPPATH\/Config\/View.php"},{"name":"YearModel.php","path":"APPPATH\/Models\/YearModel.php"},{"name":"autoload.php","path":"VENDORPATH\/autoload.php"},{"name":"autoload_real.php","path":"VENDORPATH\/composer\/autoload_real.php"},{"name":"autoload_static.php","path":"VENDORPATH\/composer\/autoload_static.php"},{"name":"deep_copy.php","path":"VENDORPATH\/myclabs\/deep-copy\/src\/DeepCopy\/deep_copy.php"},{"name":"development.php","path":"APPPATH\/Config\/Boot\/development.php"},{"name":"function.php","path":"VENDORPATH\/symfony\/deprecation-contracts\/function.php"},{"name":"index.php","path":"FCPATH\/index.php"},{"name":"installed.php","path":"VENDORPATH\/composer\/installed.php"},{"name":"platform_check.php","path":"VENDORPATH\/composer\/platform_check.php"}]},"badgeValue":149,"isEmpty":false,"hasTabContent":true,"hasLabel":false,"icon":"data:image\/png;base64,iVBORw0KGgoAAAANSUhEUgAAABgAAAAYCAYAAADgdz34AAAAAXNSR0IArs4c6QAAAARnQU1BAACxjwv8YQUAAAAJcEhZcwAADsMAAA7DAcdvqGQAAAGBSURBVEhL7ZQ9S8NQGIVTBQUncfMfCO4uLgoKbuKQOWg+OkXERRE1IAXrIHbVDrqIDuLiJgj+gro7S3dnpfq88b1FMTE3VZx64HBzzvvZWxKnj15QCcPwCD5HUfSWR+JtzgmtsUcQBEva5IIm9SwSu+95CAWbUuy67qBa32ByZEDpIaZYZSZMjjQuPcQUq8yEyYEb8FSerYeQVGbAFzJkX1PyQWLhgCz0BxTCekC1Wp0hsa6yokzhed4oje6Iz6rlJEkyIKfUEFtITVtQdAibn5rMyaYsMS+a5wTv8qeXMhcU16QZbKgl3hbs+L4\/pnpdc87MElZgq10p5DxGdq8I7xrvUWUKvG3NbSK7ubngYzdJwSsF7TiOh9VOgfcEz1UayNe3JUPM1RWC5GXYgTfc75B4NBmXJnAtTfpABX0iPvEd9ezALwkplCFXcr9styiNOKc1RRZpaPM9tcqBwlWzGY1qPL9wjqRBgF5BH6j8HWh2S7MHlX8PrmbK+k\/8PzjOOzx1D3i1pKTTAAAAAElFTkSuQmCC","hasTimelineData":false,"timelineData":[]},{"title":"Routes","titleSafe":"routes","titleDetails":"","display":{"matchedRoute":[{"directory":"","controller":"\\App\\Controllers\\StatistiqueController","method":"statistique1","paramCount":1,"truePCount":1,"params":[{"name":"$id_school = ","value":"0"}]}],"routes":[{"method":"GET","route":"\/","handler":"\\App\\Controllers\\Home::login"},{"method":"GET","route":"add-user","handler":"\\App\\Controllers\\Home::addUser"},{"method":"GET","route":"Home","handler":"\\App\\Controllers\\Home::home"},{"method":"GET","route":"Home2","handler":"\\App\\Controllers\\Home::home2"},{"method":"GET","route":"Licence","handler":"\\App\\Controllers\\Home::licence"},{"method":"GET","route":"log-out-user","handler":"\\App\\Controllers\\AuthController::logOut"},{"method":"GET","route":"shool-choice-user","handler":"\\App\\Controllers\\Home::choiceSchool"},{"method":"GET","route":"Profile_student\/(.*)","handler":"\\App\\Controllers\\StudentController::profile_student\/$1"},{"method":"GET","route":"Note","handler":"\\App\\Controllers\\Home::note"},{"method":"GET","route":"user","handler":"\\App\\Controllers\\UserController::index"},{"method":"GET","route":"user\/add-user","handler":"\\App\\Controllers\\UserController::addUser"},{"method":"GET","route":"user\/attach-user","handler":"\\App\\Controllers\\UserController::attachUserFonct"},{"method":"GET","route":"user\/list-all-user","handler":"\\App\\Controllers\\UserController::listAllUser"},{"method":"GET","route":"user\/list-user-actif","handler":"\\App\\Controllers\\UserController::listUserActif"},{"method":"GET","route":"user\/list-user-inactif","handler":"\\App\\Controllers\\UserController::listUserInactif"},{"method":"GET","route":"user\/list-user-delete","handler":"\\App\\Controllers\\UserController::listUserDelete"},{"method":"GET","route":"user\/list-user-not-delete","handler":"\\App\\Controllers\\UserController::listUserNotDelete"},{"method":"GET","route":"user\/attach-user-fonct\/(.*)\/(.*)","handler":"\\App\\Controllers\\UserController::attachUserFonct\/$1\/$2"},{"method":"GET","route":"auth\/auth-user","handler":"\\App\\Controllers\\AuthController::authentification"},{"method":"GET","route":"statistique\/acceuil1\/(.*)","handler":"\\App\\Controllers\\StatistiqueController::statistique1\/$1"},{"method":"GET","route":"statistique\/diagramme_effectif\/(.*)","handler":"\\App\\Controllers\\StatistiqueController::Diagramme_effectif\/$1"},{"method":"GET","route":"school\/save","handler":"\\App\\Controllers\\Home::save"},{"method":"GET","route":"school\/list","handler":"\\App\\Controllers\\Home::liste"},{"method":"GET","route":"school\/insert","handler":"\\App\\Controllers\\SchoolController::insertschool"},{"method":"GET","route":"school\/update","handler":"\\App\\Controllers\\SchoolController::updateschool"},{"method":"GET","route":"school\/select\/(.*)","handler":"\\App\\Controllers\\SchoolController::selectschool\/$1"},{"method":"GET","route":"school\/delete\/(.*)","handler":"\\App\\Controllers\\SchoolController::deleteschool\/$1"},{"method":"GET","route":"school\/AllSchool\/(.*)","handler":"\\App\\Controllers\\SchoolController::liste_school\/$1"},{"method":"GET","route":"school\/SchoolFilter\/(.*)","handler":"\\App\\Controllers\\SchoolController::school_filter\/$1"},{"method":"GET","route":"scolarite\/historique_paiement","handler":"\\App\\Controllers\\ScolariteController::historique_paiement"},{"method":"GET","route":"scolarite\/save_bourse","handler":"\\App\\Controllers\\ScolariteController::save_bourse"},{"method":"GET","route":"scolarite\/save_inscription","handler":"\\App\\Controllers\\ScolariteController::save_inscription"},{"method":"GET","route":"scolarite\/save_pension","handler":"\\App\\Controllers\\ScolariteController::save_pension"},{"method":"GET","route":"scolarite\/Payer_inscription","handler":"\\App\\Controllers\\ScolariteController::payer_inscription"},{"method":"GET","route":"scolarite\/Payer_scolarite","handler":"\\App\\Controllers\\ScolariteController::payer_scolarite"},{"method":"GET","route":"scolarite\/Statistique_scolarite","handler":"\\App\\Controllers\\ScolariteController::statistique_scolarite"},{"method":"GET","route":"scolarite\/Montant_scolarite","handler":"\\App\\Controllers\\ScolariteController::montant_scolarite"},{"method":"GET","route":"scolarite\/Print_stat_scolarite","handler":"\\App\\Controllers\\ScolariteController::print_stat_scolarite"},{"method":"GET","route":"scolarite\/Payer_montant_scolarite","handler":"\\App\\Controllers\\ScolariteController::payer_montant_scolarite"},{"method":"GET","route":"scolarite\/AllClas\/(.*)\/(.*)\/(.*)","handler":"\\App\\Controllers\\ScolariteController::allClassMontant\/$1\/$2\/$3"},{"method":"GET","route":"scolarite\/Enregistrer_bourse","handler":"\\App\\Controllers\\ScolariteController::enregistrer_bourse"},{"method":"GET","route":"scolarite\/List_bourse","handler":"\\App\\Controllers\\ScolariteController::list_bourse"},{"method":"GET","route":"scolarite\/RecapPayement\/(.*)\/(.*)\/(.*)\/(.*)\/(.*)","handler":"\\App\\Controllers\\ScolariteController::recap_payement\/$1\/$2\/$3\/$4\/$5"},{"method":"GET","route":"scolarite\/AllPaiement\/(.*)\/(.*)","handler":"\\App\\Controllers\\ScolariteController::allPaiement\/$1\/$2"},{"method":"GET","route":"scolarite\/delete\/(.*)","handler":"\\App\\Controllers\\ScolariteController::deletePaiement\/$1"},{"method":"GET","route":"scolarite\/getOne\/(.*)","handler":"\\App\\Controllers\\ScolariteController::getOne\/$1"},{"method":"GET","route":"scolarite\/update","handler":"\\App\\Controllers\\ScolariteController::updatePaiement"},{"method":"GET","route":"student\/GiveBourses","handler":"\\App\\Controllers\\StudentController::giveBourses"},{"method":"GET","route":"student\/deliberation","handler":"\\App\\Controllers\\StudentController::deliberation"},{"method":"GET","route":"student\/basculeNextYear","handler":"\\App\\Controllers\\StudentController::basculeNextYear"},{"method":"GET","route":"student\/save","handler":"\\App\\Controllers\\StudentController::save"},{"method":"GET","route":"student\/list","handler":"\\App\\Controllers\\StudentController::liste"},{"method":"GET","route":"student\/ChangePhoto","handler":"\\App\\Controllers\\StudentController::change_photo"},{"method":"GET","route":"student\/Importer","handler":"\\App\\Controllers\\StudentController::importer_liste"},{"method":"GET","route":"student\/insertPhoto","handler":"\\App\\Controllers\\StudentController::insert_photo"},{"method":"GET","route":"student\/insertMatieres","handler":"\\App\\Controllers\\StudentController::insert_matieres"},{"method":"GET","route":"student\/importStudent","handler":"\\App\\Controllers\\StudentController::import_student"},{"method":"GET","route":"student\/getOne\/(.*)\/(.*)\/(.*)\/(.*)\/(.*)","handler":"\\App\\Controllers\\StudentController::get_one_student\/$1\/$2\/$3\/$4\/$5"},{"method":"GET","route":"student\/insert","handler":"\\App\\Controllers\\StudentController::insertstudent"},{"method":"GET","route":"student\/update","handler":"\\App\\Controllers\\StudentController::updatestudent"},{"method":"GET","route":"student\/delete\/(.*)","handler":"\\App\\Controllers\\StudentController::delete_user\/$1"},{"method":"GET","route":"student\/AllStudent\/(.*)","handler":"\\App\\Controllers\\StudentController::liste_student\/$1"},{"method":"GET","route":"student\/AllStudentSchool\/(.*)","handler":"\\App\\Controllers\\StudentController::liste_student_school\/$1"},{"method":"GET","route":"student\/StudentFilter","handler":"\\App\\Controllers\\StudentController::student_filter"},{"method":"GET","route":"student\/PrintListClass\/(.*)\/(.*)\/(.*)\/(.*)","handler":"\\App\\Controllers\\StudentController::print_list_class\/$1\/$2\/$3\/$4"},{"method":"GET","route":"student\/PrintAllBordereaux\/(.*)\/(.*)\/(.*)\/(.*)","handler":"\\App\\Controllers\\StudentController::print_bordereau_notes\/$1\/$2\/$3\/$4"},{"method":"GET","route":"student\/PrintListClassRedouble\/(.*)\/(.*)\/(.*)\/(.*)","handler":"\\App\\Controllers\\StudentController::print_list_redouble\/$1\/$2\/$3\/$4"},{"method":"GET","route":"student\/PrintListClassNew\/(.*)\/(.*)\/(.*)\/(.*)","handler":"\\App\\Controllers\\StudentController::print_list_new\/$1\/$2\/$3\/$4"},{"method":"GET","route":"student\/PrintFichePress\/(.*)\/(.*)\/(.*)\/(.*)","handler":"\\App\\Controllers\\StudentController::print_fiche_pres\/$1\/$2\/$3\/$4"},{"method":"GET","route":"student\/PrintFicheDecharge\/(.*)\/(.*)\/(.*)\/(.*)","handler":"\\App\\Controllers\\StudentController::print_fiche_decharge\/$1\/$2\/$3\/$4"},{"method":"GET","route":"student\/PrintFicheInscription\/(.*)\/(.*)\/(.*)\/(.*)","handler":"\\App\\Controllers\\StudentController::print_fiche_inscrit\/$1\/$2\/$3\/$4"},{"method":"GET","route":"student\/PrintFicheNotInscription\/(.*)\/(.*)\/(.*)\/(.*)","handler":"\\App\\Controllers\\StudentController::print_fiche_not_inscrit\/$1\/$2\/$3\/$4"},{"method":"GET","route":"student\/PrintFicheCertificat\/(.*)\/(.*)\/(.*)\/(.*)","handler":"\\App\\Controllers\\CertificatController::print_certificat_class\/$1\/$2\/$3\/$4"},{"method":"GET","route":"student\/PrintCarteScolaire\/(.*)\/(.*)\/(.*)\/(.*)","handler":"\\App\\Controllers\\PrintCarteControl::print_carte_class\/$1\/$2\/$3\/$4"},{"method":"GET","route":"student\/PrintFicheCertificatOne\/(.*)\/(.*)\/(.*)\/(.*)\/(.*)","handler":"\\App\\Controllers\\CertificatController::print_certificat_class_one\/$1\/$2\/$3\/$4\/$5"},{"method":"GET","route":"student\/PrintOneCarteScolaire\/(.*)\/(.*)\/(.*)\/(.*)\/(.*)","handler":"\\App\\Controllers\\PrintCarteControl::print_carte_class_one\/$1\/$2\/$3\/$4\/$5"},{"method":"GET","route":"student\/GiveMatiere","handler":"\\App\\Controllers\\StudentController::giveMatiere"},{"method":"GET","route":"student\/PrintAllBulletin\/(.*)\/(.*)\/(.*)\/(.*)\/(.*)\/(.*)\/(.*)\/(.*)","handler":"\\App\\Controllers\\StudentController::print_all_bulletin\/$1\/$2\/$3\/$4\/$5\/$6\/$7\/$8"},{"method":"GET","route":"document\/save","handler":"\\App\\Controllers\\DocumentController::save"},{"method":"GET","route":"document\/list","handler":"\\App\\Controllers\\DocumentController::liste"},{"method":"GET","route":"document\/insert","handler":"\\App\\Controllers\\DocumentController::insertdocument"},{"method":"GET","route":"document\/update","handler":"\\App\\Controllers\\DocumentController::updatedocument"},{"method":"GET","route":"document\/delete\/(.*)","handler":"\\App\\Controllers\\DocumentController::deletedocument\/$1"},{"method":"GET","route":"document\/all\/(.*)\/(.*)","handler":"\\App\\Controllers\\DocumentController::allDocument\/$1\/$2"},{"method":"GET","route":"history\/listView","handler":"\\App\\Controllers\\HistoryController::liste"},{"method":"GET","route":"history\/list","handler":"\\App\\Controllers\\HistoryController::listeMyHistory"},{"method":"GET","route":"class\/save","handler":"\\App\\Controllers\\ClassController::save"},{"method":"GET","route":"class\/list","handler":"\\App\\Controllers\\ClassController::liste"},{"method":"GET","route":"class\/insert","handler":"\\App\\Controllers\\ClassController::insertclass"},{"method":"GET","route":"class\/update","handler":"\\App\\Controllers\\ClassController::updateclass"},{"method":"GET","route":"class\/getOnclasse\/(.*)\/(.*)\/(.*)","handler":"\\App\\Controllers\\ClassController::getOneClassAndTeacher\/$1\/$2\/$3"},{"method":"GET","route":"class\/delete\/(.*)","handler":"\\App\\Controllers\\ClassController::deleteclass\/$1"},{"method":"GET","route":"class\/all\/(.*)\/(.*)\/(.*)","handler":"\\App\\Controllers\\ClassController::allClass\/$1\/$2\/$3"},{"method":"GET","route":"class\/getClassSchoolYear\/(.*)\/(.*)\/(.*)","handler":"\\App\\Controllers\\ClassController::getClassSchoolYearControl\/$1\/$2\/$3"},{"method":"GET","route":"teacher\/save","handler":"\\App\\Controllers\\TeacherController::save"},{"method":"GET","route":"teacher\/Importer","handler":"\\App\\Controllers\\TeacherController::importer"},{"method":"GET","route":"teacher\/list","handler":"\\App\\Controllers\\TeacherController::liste"},{"method":"GET","route":"teacher\/giveClass","handler":"\\App\\Controllers\\TeacherController::GiveClass"},{"method":"GET","route":"teacher\/giveSubjet","handler":"\\App\\Controllers\\TeacherController::GiveSubjet"},{"method":"GET","route":"teacher\/Importer_teacher","handler":"\\App\\Controllers\\TeacherController::impoter_eacher"},{"method":"GET","route":"teacher\/insert","handler":"\\App\\Controllers\\TeacherController::insertteacher"},{"method":"GET","route":"teacher\/all\/(.*)\/(.*)","handler":"\\App\\Controllers\\TeacherController::allTeacher\/$1\/$2"},{"method":"GET","route":"teacher\/getTeacherSchoolClass\/(.*)\/(.*)\/(.*)","handler":"\\App\\Controllers\\TeacherController::GetTeacherSchoolClass\/$1\/$2\/$3"},{"method":"GET","route":"teacher\/getTeacherSchoolClassSubject\/(.*)\/(.*)\/(.*)\/(.*)","handler":"\\App\\Controllers\\TeacherController::GetTeacherSchoolClassSubject\/$1\/$2\/$3\/$4"},{"method":"GET","route":"teacher\/update","handler":"\\App\\Controllers\\TeacherController::updateteacher"},{"method":"GET","route":"teacher\/delete\/(.*)","handler":"\\App\\Controllers\\TeacherController::deleteteacher\/$1"},{"method":"GET","route":"teacher\/PrintListSchool\/(.*)","handler":"\\App\\Controllers\\TeacherController::print_listSchool\/$1"},{"method":"GET","route":"teacher\/PrintListTeacherVaccataire\/(.*)","handler":"\\App\\Controllers\\TeacherController::PrintListTeacherVaccataire\/$1"},{"method":"GET","route":"teacher\/PrintListTeacherPermanent\/(.*)","handler":"\\App\\Controllers\\TeacherController::PrintListTeacherPermanent\/$1"},{"method":"GET","route":"teacher\/PrintContrat\/(.*)","handler":"\\App\\Controllers\\TeacherController::PrintContrat\/$1"},{"method":"GET","route":"teacher\/PrintOneContrat\/(.*)\/(.*)\/(.*)","handler":"\\App\\Controllers\\TeacherController::printOneContrat\/$1\/$2\/$3"},{"method":"GET","route":"teacher\/PrintFichePaie\/(.*)","handler":"\\App\\Controllers\\TeacherController::PrintFichePaie\/$1"},{"method":"GET","route":"teacher\/PrintFicheDecharge\/(.*)","handler":"\\App\\Controllers\\TeacherController::printFicheDecharge\/$1"},{"method":"GET","route":"teacher\/Attribution_class","handler":"\\App\\Controllers\\TeacherController::attribution_class"},{"method":"GET","route":"teacher\/Attribution_subject","handler":"\\App\\Controllers\\TeacherController::attribution_subject"},{"method":"GET","route":"teacher\/salary","handler":"\\App\\Controllers\\TeacherController::salaire_personnel"},{"method":"GET","route":"teacher\/save_salaire","handler":"\\App\\Controllers\\TeacherController::Save_salaire"},{"method":"GET","route":"teacher\/FindAllPersonnelBySchool\/(.*)","handler":"\\App\\Controllers\\TeacherController::findAllPersonnelBySchool\/$1"},{"method":"GET","route":"teacher\/HistoriqueSalaire","handler":"\\App\\Controllers\\TeacherController::historiqueSalaire"},{"method":"GET","route":"teacher\/Payer_salaire","handler":"\\App\\Controllers\\TeacherController::payer_salaire"},{"method":"GET","route":"teaching_unit\/save","handler":"\\App\\Controllers\\TeachingUnitController::save"},{"method":"GET","route":"teaching_unit\/list","handler":"\\App\\Controllers\\TeachingUnitController::liste"},{"method":"GET","route":"teaching_unit\/insert","handler":"\\App\\Controllers\\TeachingUnitController::insertteaching"},{"method":"GET","route":"teaching_unit\/all\/(.*)","handler":"\\App\\Controllers\\TeachingUnitController::allTeachingUnit\/$1"},{"method":"GET","route":"teaching_unit\/AllByTeacher\/(.*)\/(.*)","handler":"\\App\\Controllers\\TeachingUnitController::allTeachingUnitByTeacher\/$1\/$2"},{"method":"GET","route":"teaching_unit\/update","handler":"\\App\\Controllers\\TeachingUnitController::updateTeachingUnit"},{"method":"GET","route":"teaching_unit\/delete\/(.*)","handler":"\\App\\Controllers\\TeachingUnitController::deleteteachingUnit\/$1"},{"method":"GET","route":"teaching_unit\/one\/(.*)","handler":"\\App\\Controllers\\TeachingUnitController::GetOne\/$1"},{"method":"GET","route":"teaching_unit\/ByClass\/(.*)","handler":"\\App\\Controllers\\TeachingUnitController::allTeachingUnit\/$1"},{"method":"GET","route":"years\/save","handler":"\\App\\Controllers\\YearController::save"},{"method":"GET","route":"years\/list","handler":"\\App\\Controllers\\YearController::liste"},{"method":"GET","route":"years\/insert","handler":"\\App\\Controllers\\YearController::insertyear"},{"method":"GET","route":"years\/actif","handler":"\\App\\Controllers\\YearController::yearActif"},{"method":"GET","route":"years\/update","handler":"\\App\\Controllers\\YearController::updateyear"},{"method":"GET","route":"years\/delete\/(.*)","handler":"\\App\\Controllers\\YearController::deleteyear\/$1"},{"method":"GET","route":"years\/active\/(.*)","handler":"\\App\\Controllers\\YearController::activeyear\/$1"},{"method":"GET","route":"years\/all","handler":"\\App\\Controllers\\YearController::allYear"},{"method":"GET","route":"years\/one\/(.*)","handler":"\\App\\Controllers\\YearController::oneYear\/$1"},{"method":"GET","route":"sequence\/save","handler":"\\App\\Controllers\\SequenceController::save"},{"method":"GET","route":"sequence\/list","handler":"\\App\\Controllers\\SequenceController::liste"},{"method":"GET","route":"sequence\/insert","handler":"\\App\\Controllers\\SequenceController::insertsequence"},{"method":"GET","route":"sequence\/all\/(.*)","handler":"\\App\\Controllers\\SequenceController::allsequence\/$1"},{"method":"GET","route":"sequence\/all-filter\/(.*)\/(.*)\/(.*)\/(.*)\/(.*)","handler":"\\App\\Controllers\\SequenceController::allFiltersequence\/$1\/$2\/$3\/$4\/$5"},{"method":"GET","route":"sequence\/update","handler":"\\App\\Controllers\\SequenceController::updatesequence"},{"method":"GET","route":"sequence\/delete\/(.*)","handler":"\\App\\Controllers\\SequenceController::deletesequence\/$1"},{"method":"GET","route":"cycle\/save","handler":"\\App\\Controllers\\CycleController::save"},{"method":"GET","route":"cycle\/list","handler":"\\App\\Controllers\\CycleController::liste"},{"method":"GET","route":"cycle\/insert","handler":"\\App\\Controllers\\CycleController::insertcycle"},{"method":"GET","route":"cycle\/update","handler":"\\App\\Controllers\\CycleController::updatecycle"},{"method":"GET","route":"cycle\/delete\/(.*)","handler":"\\App\\Controllers\\CycleController::deletecycle\/$1"},{"method":"GET","route":"cycle\/all\/(.*)\/(.*)","handler":"\\App\\Controllers\\CycleController::allCycle\/$1\/$2"},{"method":"GET","route":"session\/save","handler":"\\App\\Controllers\\SessionController::save"},{"method":"GET","route":"session\/list","handler":"\\App\\Controllers\\SessionController::liste"},{"method":"GET","route":"session\/insert","handler":"\\App\\Controllers\\SessionController::insertsession"},{"method":"GET","route":"session\/all\/(.*)","handler":"\\App\\Controllers\\SessionController::allsession\/$1"},{"method":"GET","route":"serie\/save","handler":"\\App\\Controllers\\SerieController::save"},{"method":"GET","route":"serie\/list","handler":"\\App\\Controllers\\SerieController::liste"},{"method":"GET","route":"serie\/insert","handler":"\\App\\Controllers\\SerieController::insertserie"},{"method":"GET","route":"serie\/all\/(.*)","handler":"\\App\\Controllers\\SerieController::allSerie\/$1"},{"method":"GET","route":"trimestre\/save","handler":"\\App\\Controllers\\TrimestreController::save"},{"method":"GET","route":"trimestre\/list","handler":"\\App\\Controllers\\TrimestreController::liste"},{"method":"GET","route":"trimestre\/insert","handler":"\\App\\Controllers\\TrimestreController::inserttrimestre"},{"method":"GET","route":"trimestre\/update","handler":"\\App\\Controllers\\TrimestreController::updatetrimestre"},{"method":"GET","route":"trimestre\/all\/(.*)","handler":"\\App\\Controllers\\TrimestreController::alltrimestre\/$1"},{"method":"GET","route":"trimestre\/all-filter\/(.*)\/(.*)\/(.*)\/(.*)","handler":"\\App\\Controllers\\TrimestreController::alltrimestreFilter\/$1\/$2\/$3\/$4"},{"method":"GET","route":"trimestre\/delete\/(.*)","handler":"\\App\\Controllers\\TrimestreController::deletetrimestre\/$1"},{"method":"GET","route":"teachingunit\/save","handler":"\\App\\Controllers\\TeachingUnitController::save"},{"method":"GET","route":"teachingunit\/list","handler":"\\App\\Controllers\\TeachingUnitController::liste"},{"method":"GET","route":"teachingunit\/insert","handler":"\\App\\Controllers\\TeachingUnitController::insertteaching"},{"method":"GET","route":"teachingunit\/update","handler":"\\App\\Controllers\\TeachingUnitController::updateteaching"},{"method":"GET","route":"teachingunit\/all\/(.*)","handler":"\\App\\Controllers\\TeachingUnitController::allteaching\/$1\/$2\/$3\/$4"},{"method":"GET","route":"teachingunit\/allothers\/(.*)","handler":"\\App\\Controllers\\TeachingUnitController::allteachingOther\/$1\/$2\/$3\/$4"},{"method":"GET","route":"teachingunit\/delete\/(.*)","handler":"\\App\\Controllers\\TeachingUnitController::deleteteaching\/$1"},{"method":"GET","route":"teacher\/all\/(.*)","handler":"\\App\\Controllers\\TeacherController::allteacher\/$1"},{"method":"GET","route":"note\/imprimer_bulletin","handler":"\\App\\Controllers\\NoteController::imprimer_bulletin"},{"method":"GET","route":"note\/save","handler":"\\App\\Controllers\\NoteController::save"},{"method":"GET","route":"note\/list","handler":"\\App\\Controllers\\NoteController::liste"},{"method":"GET","route":"note\/insert","handler":"\\App\\Controllers\\NoteController::insertnote"},{"method":"GET","route":"note\/getnoteByTeachingUnit\/(.*)\/(.*)\/(.*)","handler":"\\App\\Controllers\\NoteController::GetnoteByTeachingUnit\/$1\/$2\/$3"},{"method":"GET","route":"note\/update","handler":"\\App\\Controllers\\NoteController::updatenote"},{"method":"GET","route":"note\/Selectnote","handler":"\\App\\Controllers\\NoteController::listenote"},{"method":"GET","route":"payment\/save","handler":"\\App\\Controllers\\PaymentController::save"},{"method":"GET","route":"payment\/list","handler":"\\App\\Controllers\\PaymentController::liste"},{"method":"GET","route":"payment\/insert","handler":"\\App\\Controllers\\PaymentController::insertpayment"},{"method":"GET","route":"payment\/update","handler":"\\App\\Controllers\\PaymentController::updatepayment"},{"method":"GET","route":"payment\/all\/(.*)","handler":"\\App\\Controllers\\PaymentController::allpayment\/$1\/$2\/$3\/$4\/$5"},{"method":"GET","route":"fonctionnality\/default","handler":"\\App\\Controllers\\FonctionnlityController::defaultFonctionnality"},{"method":"GET","route":"fonctionnality\/add-fonctionnality","handler":"\\App\\Controllers\\FonctionnlityController::addFonctionnality"},{"method":"GET","route":"fonctionnality\/attach-fonctionnality\/(.*)\/(.*)","handler":"\\App\\Controllers\\FonctionnlityController::atachFonct\/$1\/$2"},{"method":"POST","route":"user\/add-user","handler":"\\App\\Controllers\\UserController::addUser"},{"method":"POST","route":"user\/attach-user","handler":"\\App\\Controllers\\UserController::attachUserFonct"},{"method":"POST","route":"user\/list-all-user","handler":"\\App\\Controllers\\UserController::listAllUser"},{"method":"POST","route":"user\/list-user-actif","handler":"\\App\\Controllers\\UserController::listUserActif"},{"method":"POST","route":"user\/list-user-inactif","handler":"\\App\\Controllers\\UserController::listUserInactif"},{"method":"POST","route":"user\/list-user-delete","handler":"\\App\\Controllers\\UserController::listUserDelete"},{"method":"POST","route":"user\/list-user-not-delete","handler":"\\App\\Controllers\\UserController::listUserNotDelete"},{"method":"POST","route":"user\/attach-user-fonct\/(.*)\/(.*)","handler":"\\App\\Controllers\\UserController::attachUserFonct\/$1\/$2"},{"method":"POST","route":"auth\/auth-user","handler":"\\App\\Controllers\\AuthController::authentification"},{"method":"POST","route":"statistique\/acceuil1\/(.*)","handler":"\\App\\Controllers\\StatistiqueController::statistique1\/$1"},{"method":"POST","route":"statistique\/diagramme_effectif\/(.*)","handler":"\\App\\Controllers\\StatistiqueController::Diagramme_effectif\/$1"},{"method":"POST","route":"school\/insert","handler":"\\App\\Controllers\\SchoolController::insertschool"},{"method":"POST","route":"school\/update","handler":"\\App\\Controllers\\SchoolController::updateschool"},{"method":"POST","route":"school\/select\/(.*)","handler":"\\App\\Controllers\\SchoolController::selectschool\/$1"},{"method":"POST","route":"school\/delete\/(.*)","handler":"\\App\\Controllers\\SchoolController::deleteschool\/$1"},{"method":"POST","route":"school\/AllSchool\/(.*)","handler":"\\App\\Controllers\\SchoolController::liste_school\/$1"},{"method":"POST","route":"school\/SchoolFilter\/(.*)","handler":"\\App\\Controllers\\SchoolController::school_filter\/$1"},{"method":"POST","route":"scolarite\/Payer_inscription","handler":"\\App\\Controllers\\ScolariteController::payer_inscription"},{"method":"POST","route":"scolarite\/Payer_scolarite","handler":"\\App\\Controllers\\ScolariteController::payer_scolarite"},{"method":"POST","route":"scolarite\/Statistique_scolarite","handler":"\\App\\Controllers\\ScolariteController::statistique_scolarite"},{"method":"POST","route":"scolarite\/Montant_scolarite","handler":"\\App\\Controllers\\ScolariteController::montant_scolarite"},{"method":"POST","route":"scolarite\/Print_stat_scolarite","handler":"\\App\\Controllers\\ScolariteController::print_stat_scolarite"},{"method":"POST","route":"scolarite\/Payer_montant_scolarite","handler":"\\App\\Controllers\\ScolariteController::payer_montant_scolarite"},{"method":"POST","route":"scolarite\/AllClas\/(.*)\/(.*)\/(.*)","handler":"\\App\\Controllers\\ScolariteController::allClassMontant\/$1\/$2\/$3"},{"method":"POST","route":"scolarite\/Enregistrer_bourse","handler":"\\App\\Controllers\\ScolariteController::enregistrer_bourse"},{"method":"POST","route":"scolarite\/List_bourse","handler":"\\App\\Controllers\\ScolariteController::list_bourse"},{"method":"POST","route":"scolarite\/RecapPayement\/(.*)\/(.*)\/(.*)\/(.*)\/(.*)","handler":"\\App\\Controllers\\ScolariteController::recap_payement\/$1\/$2\/$3\/$4\/$5"},{"method":"POST","route":"scolarite\/AllPaiement\/(.*)\/(.*)","handler":"\\App\\Controllers\\ScolariteController::allPaiement\/$1\/$2"},{"method":"POST","route":"scolarite\/delete\/(.*)","handler":"\\App\\Controllers\\ScolariteController::deletePaiement\/$1"},{"method":"POST","route":"scolarite\/getOne\/(.*)","handler":"\\App\\Controllers\\ScolariteController::getOne\/$1"},{"method":"POST","route":"scolarite\/update","handler":"\\App\\Controllers\\ScolariteController::updatePaiement"},{"method":"POST","route":"student\/insertPhoto","handler":"\\App\\Controllers\\StudentController::insert_photo"},{"method":"POST","route":"student\/insertMatieres","handler":"\\App\\Controllers\\StudentController::insert_matieres"},{"method":"POST","route":"student\/importStudent","handler":"\\App\\Controllers\\StudentController::import_student"},{"method":"POST","route":"student\/getOne\/(.*)\/(.*)\/(.*)\/(.*)\/(.*)","handler":"\\App\\Controllers\\StudentController::get_one_student\/$1\/$2\/$3\/$4\/$5"},{"method":"POST","route":"student\/insert","handler":"\\App\\Controllers\\StudentController::insertstudent"},{"method":"POST","route":"student\/update","handler":"\\App\\Controllers\\StudentController::updatestudent"},{"method":"POST","route":"student\/delete\/(.*)","handler":"\\App\\Controllers\\StudentController::delete_user\/$1"},{"method":"POST","route":"student\/AllStudent\/(.*)","handler":"\\App\\Controllers\\StudentController::liste_student\/$1"},{"method":"POST","route":"student\/AllStudentSchool\/(.*)","handler":"\\App\\Controllers\\StudentController::liste_student_school\/$1"},{"method":"POST","route":"student\/StudentFilter","handler":"\\App\\Controllers\\StudentController::student_filter"},{"method":"POST","route":"student\/PrintListClass\/(.*)\/(.*)\/(.*)\/(.*)","handler":"\\App\\Controllers\\StudentController::print_list_class\/$1\/$2\/$3\/$4"},{"method":"POST","route":"student\/PrintAllBordereaux\/(.*)\/(.*)\/(.*)\/(.*)","handler":"\\App\\Controllers\\StudentController::print_bordereau_notes\/$1\/$2\/$3\/$4"},{"method":"POST","route":"student\/PrintListClassRedouble\/(.*)\/(.*)\/(.*)\/(.*)","handler":"\\App\\Controllers\\StudentController::print_list_redouble\/$1\/$2\/$3\/$4"},{"method":"POST","route":"student\/PrintListClassNew\/(.*)\/(.*)\/(.*)\/(.*)","handler":"\\App\\Controllers\\StudentController::print_list_new\/$1\/$2\/$3\/$4"},{"method":"POST","route":"student\/PrintFichePress\/(.*)\/(.*)\/(.*)\/(.*)","handler":"\\App\\Controllers\\StudentController::print_fiche_pres\/$1\/$2\/$3\/$4"},{"method":"POST","route":"student\/PrintFicheDecharge\/(.*)\/(.*)\/(.*)\/(.*)","handler":"\\App\\Controllers\\StudentController::print_fiche_decharge\/$1\/$2\/$3\/$4"},{"method":"POST","route":"student\/PrintFicheInscription\/(.*)\/(.*)\/(.*)\/(.*)","handler":"\\App\\Controllers\\StudentController::print_fiche_inscrit\/$1\/$2\/$3\/$4"},{"method":"POST","route":"student\/PrintFicheNotInscription\/(.*)\/(.*)\/(.*)\/(.*)","handler":"\\App\\Controllers\\StudentController::print_fiche_not_inscrit\/$1\/$2\/$3\/$4"},{"method":"POST","route":"student\/PrintFicheCertificat\/(.*)\/(.*)\/(.*)\/(.*)","handler":"\\App\\Controllers\\CertificatController::print_certificat_class\/$1\/$2\/$3\/$4"},{"method":"POST","route":"student\/PrintCarteScolaire\/(.*)\/(.*)\/(.*)\/(.*)","handler":"\\App\\Controllers\\PrintCarteControl::print_carte_class\/$1\/$2\/$3\/$4"},{"method":"POST","route":"student\/PrintFicheCertificatOne\/(.*)\/(.*)\/(.*)\/(.*)\/(.*)","handler":"\\App\\Controllers\\CertificatController::print_certificat_class_one\/$1\/$2\/$3\/$4\/$5"},{"method":"POST","route":"student\/PrintOneCarteScolaire\/(.*)\/(.*)\/(.*)\/(.*)\/(.*)","handler":"\\App\\Controllers\\PrintCarteControl::print_carte_class_one\/$1\/$2\/$3\/$4\/$5"},{"method":"POST","route":"student\/GiveBourse","handler":"\\App\\Controllers\\StudentController::giveBourse"},{"method":"POST","route":"student\/PrintAllBulletin\/(.*)\/(.*)\/(.*)\/(.*)\/(.*)\/(.*)\/(.*)\/(.*)","handler":"\\App\\Controllers\\StudentController::print_all_bulletin\/$1\/$2\/$3\/$4\/$5\/$6\/$7\/$8"},{"method":"POST","route":"document\/insert","handler":"\\App\\Controllers\\DocumentController::insertdocument"},{"method":"POST","route":"document\/update","handler":"\\App\\Controllers\\DocumentController::updatedocument"},{"method":"POST","route":"document\/delete\/(.*)","handler":"\\App\\Controllers\\DocumentController::deletedocument\/$1"},{"method":"POST","route":"document\/all\/(.*)\/(.*)","handler":"\\App\\Controllers\\DocumentController::allDocument\/$1\/$2"},{"method":"POST","route":"history\/listView","handler":"\\App\\Controllers\\HistoryController::liste"},{"method":"POST","route":"history\/list","handler":"\\App\\Controllers\\HistoryController::listeMyHistory"},{"method":"POST","route":"class\/insert","handler":"\\App\\Controllers\\ClassController::insertclass"},{"method":"POST","route":"class\/update","handler":"\\App\\Controllers\\ClassController::updateclass"},{"method":"POST","route":"class\/getOnclasse\/(.*)\/(.*)\/(.*)","handler":"\\App\\Controllers\\ClassController::getOneClassAndTeacher\/$1\/$2\/$3"},{"method":"POST","route":"class\/delete\/(.*)","handler":"\\App\\Controllers\\ClassController::deleteclass\/$1"},{"method":"POST","route":"class\/all\/(.*)\/(.*)\/(.*)","handler":"\\App\\Controllers\\ClassController::allClass\/$1\/$2\/$3"},{"method":"POST","route":"class\/getClassSchoolYear\/(.*)\/(.*)\/(.*)","handler":"\\App\\Controllers\\ClassController::getClassSchoolYearControl\/$1\/$2\/$3"},{"method":"POST","route":"teacher\/Importer_teacher","handler":"\\App\\Controllers\\TeacherController::impoter_eacher"},{"method":"POST","route":"teacher\/insert","handler":"\\App\\Controllers\\TeacherController::insertteacher"},{"method":"POST","route":"teacher\/all\/(.*)\/(.*)","handler":"\\App\\Controllers\\TeacherController::allTeacher\/$1\/$2"},{"method":"POST","route":"teacher\/getTeacherSchoolClass\/(.*)\/(.*)\/(.*)","handler":"\\App\\Controllers\\TeacherController::GetTeacherSchoolClass\/$1\/$2\/$3"},{"method":"POST","route":"teacher\/getTeacherSchoolClassSubject\/(.*)\/(.*)\/(.*)\/(.*)","handler":"\\App\\Controllers\\TeacherController::GetTeacherSchoolClassSubject\/$1\/$2\/$3\/$4"},{"method":"POST","route":"teacher\/update","handler":"\\App\\Controllers\\TeacherController::updateteacher"},{"method":"POST","route":"teacher\/delete\/(.*)","handler":"\\App\\Controllers\\TeacherController::deleteteacher\/$1"},{"method":"POST","route":"teacher\/PrintListSchool\/(.*)","handler":"\\App\\Controllers\\TeacherController::print_listSchool\/$1"},{"method":"POST","route":"teacher\/PrintListTeacherVaccataire\/(.*)","handler":"\\App\\Controllers\\TeacherController::PrintListTeacherVaccataire\/$1"},{"method":"POST","route":"teacher\/PrintListTeacherPermanent\/(.*)","handler":"\\App\\Controllers\\TeacherController::PrintListTeacherPermanent\/$1"},{"method":"POST","route":"teacher\/PrintContrat\/(.*)","handler":"\\App\\Controllers\\TeacherController::PrintContrat\/$1"},{"method":"POST","route":"teacher\/PrintOneContrat\/(.*)\/(.*)\/(.*)","handler":"\\App\\Controllers\\TeacherController::printOneContrat\/$1\/$2\/$3"},{"method":"POST","route":"teacher\/PrintFichePaie\/(.*)","handler":"\\App\\Controllers\\TeacherController::PrintFichePaie\/$1"},{"method":"POST","route":"teacher\/PrintFicheDecharge\/(.*)","handler":"\\App\\Controllers\\TeacherController::printFicheDecharge\/$1"},{"method":"POST","route":"teacher\/Attribution_class","handler":"\\App\\Controllers\\TeacherController::attribution_class"},{"method":"POST","route":"teacher\/Attribution_subject","handler":"\\App\\Controllers\\TeacherController::attribution_subject"},{"method":"POST","route":"teacher\/salary","handler":"\\App\\Controllers\\TeacherController::salaire_personnel"},{"method":"POST","route":"teacher\/save_salaire","handler":"\\App\\Controllers\\TeacherController::Save_salaire"},{"method":"POST","route":"teacher\/FindAllPersonnelBySchool\/(.*)","handler":"\\App\\Controllers\\TeacherController::findAllPersonnelBySchool\/$1"},{"method":"POST","route":"teacher\/HistoriqueSalaire","handler":"\\App\\Controllers\\TeacherController::historiqueSalaire"},{"method":"POST","route":"teacher\/Payer_salaire","handler":"\\App\\Controllers\\TeacherController::payer_salaire"},{"method":"POST","route":"teaching_unit\/insert","handler":"\\App\\Controllers\\TeachingUnitController::insertteaching"},{"method":"POST","route":"teaching_unit\/all\/(.*)","handler":"\\App\\Controllers\\TeachingUnitController::allTeachingUnit\/$1"},{"method":"POST","route":"teaching_unit\/AllByTeacher\/(.*)\/(.*)","handler":"\\App\\Controllers\\TeachingUnitController::allTeachingUnitByTeacher\/$1\/$2"},{"method":"POST","route":"teaching_unit\/update","handler":"\\App\\Controllers\\TeachingUnitController::updateTeachingUnit"},{"method":"POST","route":"teaching_unit\/delete\/(.*)","handler":"\\App\\Controllers\\TeachingUnitController::deleteteachingUnit\/$1"},{"method":"POST","route":"teaching_unit\/one\/(.*)","handler":"\\App\\Controllers\\TeachingUnitController::GetOne\/$1"},{"method":"POST","route":"teaching_unit\/ByClass\/(.*)","handler":"\\App\\Controllers\\TeachingUnitController::allTeachingUnit\/$1"},{"method":"POST","route":"years\/insert","handler":"\\App\\Controllers\\YearController::insertyear"},{"method":"POST","route":"years\/actif","handler":"\\App\\Controllers\\YearController::yearActif"},{"method":"POST","route":"years\/update","handler":"\\App\\Controllers\\YearController::updateyear"},{"method":"POST","route":"years\/delete\/(.*)","handler":"\\App\\Controllers\\YearController::deleteyear\/$1"},{"method":"POST","route":"years\/active\/(.*)","handler":"\\App\\Controllers\\YearController::activeyear\/$1"},{"method":"POST","route":"years\/all","handler":"\\App\\Controllers\\YearController::allYear"},{"method":"POST","route":"years\/one\/(.*)","handler":"\\App\\Controllers\\YearController::oneYear\/$1"},{"method":"POST","route":"sequence\/insert","handler":"\\App\\Controllers\\SequenceController::insertsequence"},{"method":"POST","route":"sequence\/all\/(.*)","handler":"\\App\\Controllers\\SequenceController::allsequence\/$1"},{"method":"POST","route":"sequence\/all-filter\/(.*)\/(.*)\/(.*)\/(.*)\/(.*)","handler":"\\App\\Controllers\\SequenceController::allFiltersequence\/$1\/$2\/$3\/$4\/$5"},{"method":"POST","route":"sequence\/update","handler":"\\App\\Controllers\\SequenceController::updatesequence"},{"method":"POST","route":"sequence\/delete\/(.*)","handler":"\\App\\Controllers\\SequenceController::deletesequence\/$1"},{"method":"POST","route":"cycle\/insert","handler":"\\App\\Controllers\\CycleController::insertcycle"},{"method":"POST","route":"cycle\/update","handler":"\\App\\Controllers\\CycleController::updatecycle"},{"method":"POST","route":"cycle\/delete\/(.*)","handler":"\\App\\Controllers\\CycleController::deletecycle\/$1"},{"method":"POST","route":"cycle\/all\/(.*)\/(.*)","handler":"\\App\\Controllers\\CycleController::allCycle\/$1\/$2"},{"method":"POST","route":"session\/insert","handler":"\\App\\Controllers\\SessionController::insertsession"},{"method":"POST","route":"session\/all\/(.*)","handler":"\\App\\Controllers\\SessionController::allsession\/$1"},{"method":"POST","route":"serie\/insert","handler":"\\App\\Controllers\\SerieController::insertserie"},{"method":"POST","route":"serie\/all\/(.*)","handler":"\\App\\Controllers\\SerieController::allSerie\/$1"},{"method":"POST","route":"trimestre\/insert","handler":"\\App\\Controllers\\TrimestreController::inserttrimestre"},{"method":"POST","route":"trimestre\/update","handler":"\\App\\Controllers\\TrimestreController::updatetrimestre"},{"method":"POST","route":"trimestre\/all\/(.*)","handler":"\\App\\Controllers\\TrimestreController::alltrimestre\/$1"},{"method":"POST","route":"trimestre\/all-filter\/(.*)\/(.*)\/(.*)\/(.*)","handler":"\\App\\Controllers\\TrimestreController::alltrimestreFilter\/$1\/$2\/$3\/$4"},{"method":"POST","route":"trimestre\/delete\/(.*)","handler":"\\App\\Controllers\\TrimestreController::deletetrimestre\/$1"},{"method":"POST","route":"teachingunit\/insert","handler":"\\App\\Controllers\\TeachingUnitController::insertteaching"},{"method":"POST","route":"teachingunit\/update","handler":"\\App\\Controllers\\TeachingUnitController::updateteaching"},{"method":"POST","route":"teachingunit\/all\/(.*)","handler":"\\App\\Controllers\\TeachingUnitController::allteaching\/$1\/$2\/$3\/$4"},{"method":"POST","route":"teachingunit\/allothers\/(.*)","handler":"\\App\\Controllers\\TeachingUnitController::allteachingOther\/$1\/$2\/$3\/$4"},{"method":"POST","route":"teachingunit\/delete\/(.*)","handler":"\\App\\Controllers\\TeachingUnitController::deleteteaching\/$1"},{"method":"POST","route":"teacher\/all\/(.*)","handler":"\\App\\Controllers\\TeacherController::allteacher\/$1"},{"method":"POST","route":"note\/insert","handler":"\\App\\Controllers\\NoteController::insertnote"},{"method":"POST","route":"note\/getnoteByTeachingUnit\/(.*)\/(.*)\/(.*)","handler":"\\App\\Controllers\\NoteController::GetnoteByTeachingUnit\/$1\/$2\/$3"},{"method":"POST","route":"note\/update","handler":"\\App\\Controllers\\NoteController::updatenote"},{"method":"POST","route":"note\/Selectnote","handler":"\\App\\Controllers\\NoteController::listenote"},{"method":"POST","route":"payment\/insert","handler":"\\App\\Controllers\\PaymentController::insertpayment"},{"method":"POST","route":"payment\/update","handler":"\\App\\Controllers\\PaymentController::updatepayment"},{"method":"POST","route":"payment\/all\/(.*)","handler":"\\App\\Controllers\\PaymentController::allpayment\/$1\/$2\/$3\/$4\/$5"},{"method":"POST","route":"fonctionnality\/default","handler":"\\App\\Controllers\\FonctionnlityController::defaultFonctionnality"},{"method":"POST","route":"fonctionnality\/add-fonctionnality","handler":"\\App\\Controllers\\FonctionnlityController::addFonctionnality"},{"method":"POST","route":"fonctionnality\/attach-fonctionnality\/(.*)\/(.*)","handler":"\\App\\Controllers\\FonctionnlityController::atachFonct\/$1\/$2"}]},"badgeValue":189,"isEmpty":false,"hasTabContent":true,"hasLabel":false,"icon":"data:image\/png;base64,iVBORw0KGgoAAAANSUhEUgAAABgAAAAYCAYAAADgdz34AAAAAXNSR0IArs4c6QAAAARnQU1BAACxjwv8YQUAAAAJcEhZcwAADsMAAA7DAcdvqGQAAAFDSURBVEhL7ZRNSsNQFIUjVXSiOFEcuQIHDpzpxC0IGYeE\/BEInbWlCHEDLsSiuANdhKDjgm6ggtSJ+l25ldrmmTwIgtgDh\/t37r1J+16cX0dRFMtpmu5pWAkrvYjjOB7AETzStBFW+inxu3KUJMmhludQpoflS1zXban4LYqiO224h6VLTHr8Z+z8EpIHFF9gG78nDVmW7UgTHKjsCyY98QP+pcq+g8Ku2s8G8X3f3\/I8b038WZTp+bO38zxfFd+I6YY6sNUvFlSDk9CRhiAI1jX1I9Cfw7GG1UB8LAuwbU0ZwQnbRDeEN5qqBxZMLtE1ti9LtbREnMIuOXnyIf5rGIb7Wq8HmlZgwYBH7ORTcKH5E4mpjeGt9fBZcHE2GCQ3Vt7oTNPNg+FXLHnSsHkw\/FR+Gg2bB8Ptzrst\/v6C\/wrH+QB+duli6MYJdQAAAABJRU5ErkJggg==","hasTimelineData":false,"timelineData":[]},{"title":"Events","titleSafe":"events","titleDetails":"","display":{"events":{"pre_system":{"event":"pre_system","duration":"0.31","count":1},"dbquery":{"event":"dbquery","duration":"0.28","count":6}}},"badgeValue":7,"isEmpty":false,"hasTabContent":true,"hasLabel":false,"icon":"data:image\/png;base64,iVBORw0KGgoAAAANSUhEUgAAABgAAAAYCAYAAADgdz34AAAAAXNSR0IArs4c6QAAAARnQU1BAACxjwv8YQUAAAAJcEhZcwAADsMAAA7DAcdvqGQAAAEASURBVEhL7ZXNDcIwDIVTsRBH1uDQDdquUA6IM1xgCA6MwJUN2hk6AQzAz0vl0ETUxC5VT3zSU5w81\/mRMGZysixbFEVR0jSKNt8geQU9aRpFmp\/keX6AbjZ5oB74vsaN5lSzA4tLSjpBFxsjeSuRy4d2mDdQTWU7YLbXTNN05mKyovj5KL6B7q3hoy3KwdZxBlT+Ipz+jPHrBqOIynZgcZonoukb\/0ckiTHqNvDXtXEAaygRbaB9FvUTjRUHsIYS0QaSp+Dw6wT4hiTmYHOcYZsdLQ2CbXa4ftuuYR4x9vYZgdb4vsFYUdmABMYeukK9\/SUme3KMFQ77+Yfzh8eYF8+orDuDWU5LAAAAAElFTkSuQmCC","hasTimelineData":true,"timelineData":[{"name":"Event: pre_system","component":"Events","start":1733841109.207761,"duration":0.00030684471130371094},{"name":"Event: dbquery","component":"Events","start":1733841109.243078,"duration":8.20159912109375e-5},{"name":"Event: dbquery","component":"Events","start":1733841109.244054,"duration":3.886222839355469e-5},{"name":"Event: dbquery","component":"Events","start":1733841109.245012,"duration":4.601478576660156e-5},{"name":"Event: dbquery","component":"Events","start":1733841109.24553,"duration":4.220008850097656e-5},{"name":"Event: dbquery","component":"Events","start":1733841109.250368,"duration":3.3855438232421875e-5},{"name":"Event: dbquery","component":"Events","start":1733841109.251419,"duration":3.886222839355469e-5}]}],"vars":{"varData":{"View Data":[]},"headers":{"Host":"localhost:8080","User-Agent":"Mozilla\/5.0 (X11; Ubuntu; Linux x86_64; rv:132.0) Gecko\/20100101 Firefox\/132.0","Accept":"application\/json, text\/javascript, *\/*; q=0.01","Accept-Language":"fr,fr-FR;q=0.8,en-US;q=0.5,en;q=0.3","Accept-Encoding":"gzip, deflate, br, zstd","Authorization":"Bearer eyJ0eXAiOiJKV1QiLCJhbGciOiJIUzI1NiJ9.eyJpc3MiOiJJc3N1ZXIgb2YgdGhlIEpXVCIsImF1ZCI6IkF1ZGllbmNlIHRoYXQgdGhlIEpXVCIsInN1YiI6IlN1YmplY3Qgb2YgdGhlIEpXVCIsImlhdCI6MTczMzg0MTEwNywiZXhwIjoxNzM0MjAxMTA3LCJlbWFpbCI6Imdhc3BhciBwYXVsIiwidHlwZSI6InVzZXIifQ.OZ0fIwDWoI6mswMBJ1o0A8k-zRFRnyWZq_brOBUIB-0","X-Requested-With":"XMLHttpRequest","Connection":"keep-alive","Referer":"http:\/\/localhost:8080\/Home","Cookie":"ci_session=6dgnemhvc69ire74uktkj36sn7k692q5","Sec-Fetch-Dest":"empty","Sec-Fetch-Mode":"cors","Sec-Fetch-Site":"same-origin"},"cookies":{"ci_session":"6dgnemhvc69ire74uktkj36sn7k692q5"},"request":"HTTP\/1.1","response":{"statusCode":200,"reason":"OK","contentType":"application\/json; charset=UTF-8","headers":{"Cache-Control":"no-store, max-age=0, no-cache","Content-Type":"application\/json; charset=UTF-8"}}},"config":{"ciVersion":"4.3.6","phpVersion":"8.1.2-1ubuntu2.18","phpSAPI":"cli-server","environment":"development","baseURL":"http:\/\/localhost:8080\/","timezone":"UTC","locale":"en","cspEnabled":false}}